construct_tracker/__init__.py
construct_tracker/cts.py
construct_tracker/data/__init__.py
construct_tracker/data/datasets/datasets_description.md
construct_tracker/data/datasets/feature_extraction/.gitkeep
construct_tracker/data/datasets/feature_extraction/reddit_4_subreddits_suicide_risk_lexicon_counts.csv
construct_tracker/data/datasets/rally_point_reddit_mental_health/rallypoint_reddit_mentalhealth_test_908.csv
construct_tracker/data/datasets/rally_point_reddit_mental_health/rallypoint_reddit_mentalhealth_train_3632.csv
construct_tracker/data/datasets/reddit_27_subreddits/.gitkeep
construct_tracker/data/datasets/reddit_27_subreddits/rmhd_27subreddits_1040posts_train.csv
construct_tracker/data/datasets/reddit_27_subreddits/rmhd_27subreddits_260posts_test.csv
construct_tracker/data/lexicons/lexicon_description.md
construct_tracker/data/lexicons/seance/SEANCE User Manual (revised 6-18-2018).docx
construct_tracker/data/lexicons/seance/clean_seance_names.csv
construct_tracker/data/lexicons/seance/data_files/affective_list.txt
construct_tracker/data/lexicons/seance/data_files/affective_norms.txt
construct_tracker/data/lexicons/seance/data_files/e_lemma_py_format_lower.txt
construct_tracker/data/lexicons/seance/data_files/emoji_utf8_lexicon.txt
construct_tracker/data/lexicons/seance/data_files/inquirerbasic.txt
construct_tracker/data/lexicons/seance/data_files/negative_words.txt
construct_tracker/data/lexicons/seance/data_files/positive_words.txt
construct_tracker/data/lexicons/seance/data_files/senticnet_data.txt
construct_tracker/data/lexicons/seance/data_files/vaderSentiment.py
construct_tracker/data/lexicons/seance/data_files/vader_lexicon.txt
construct_tracker/data/lexicons/seance/inquirerbasic.txt
construct_tracker/data/lexicons/suicide_risk_lexicon_v1-0/human_ratings/suicide_risk_lexicon_calibrated_matched_tokens_with_unmatched_unvalidated_24-02-09T15-42-48_annotation_dc.xlsx
construct_tracker-1.0.16.dist-info/LICENSE
construct_tracker-1.0.16.dist-info/METADATA
construct_tracker-1.0.16.dist-info/WHEEL
construct_tracker-1.0.16.dist-info/RECORD
