Metadata-Version: 2.3
Name: construct-tracker
Version: 1.0.16
Summary: Track and measure constructs, concepts or categories in text documents.
License: Apache-2.0
Keywords: lexicon,concept,classification,NLP,embeddings,similarity,zero shot,construct,category,social sciences,text
Author: Daniel M. Low
Author-email: daniel.m.low@gmail.com
Maintainer: Daniel M. Low
Maintainer-email: daniel.m.low@gmail.com
Requires-Python: >=3.9,<3.12
Classifier: Development Status :: 3 - Alpha
Classifier: License :: OSI Approved :: Apache Software License
Classifier: Operating System :: OS Independent
Classifier: Programming Language :: Python :: 3
Classifier: Programming Language :: Python :: 3.9
Classifier: Programming Language :: Python :: 3.10
Classifier: Programming Language :: Python :: 3.11
Requires-Dist: cython (>=0.29.24)
Requires-Dist: dill (>=0.3.0,<0.4.0)
Requires-Dist: litellm (>=1.35.28,<2.0.0)
Requires-Dist: nltk (>=3.8,<4.0)
Requires-Dist: numpy (==1.24.4)
Requires-Dist: pandas (==1.5.3)
Requires-Dist: seaborn (>=0.12.0,<0.13.0)
Requires-Dist: sentence-transformers (>=2.7,<3.0)
Requires-Dist: spacy (>=3.7.3,<3.8.0)
Requires-Dist: statsmodels (>=0.14.2,<0.15.0)
Project-URL: Documentation, https://danielmlow.github.io/construct-tracker/
Project-URL: Repository, https://github.com/danielmlow/construct-tracker
